pytest_sofaepione/__init__.py
pytest_sofaepione/module.py
pytest_sofaepione-0.1.2.dist-info/LICENSE
pytest_sofaepione-0.1.2.dist-info/METADATA
pytest_sofaepione-0.1.2.dist-info/WHEEL
pytest_sofaepione-0.1.2.dist-info/top_level.txt
pytest_sofaepione-0.1.2.dist-info/RECORD
