Metadata-Version: 2.1
Name: pytest_sofaepione
Version: 0.1.2
Summary: Test the installation of SOFA and the SofaEpione plugin.
Home-page: https://gitlab.inria.fr/epione/SofaEpione
Author: Gaëtan Desrues
Author-email: gaetan.desrues@inria.fr
License: UNKNOWN
Platform: UNKNOWN
Classifier: Programming Language :: Python :: 3
Classifier: License :: OSI Approved :: MIT License
Classifier: Operating System :: OS Independent
License-File: LICENSE
